sm_diarization_metrics/__init__.py
sm_diarization_metrics/cli.py
sm_diarization_metrics/cookbook.py
sm_diarization_metrics/utils.py
sm_diarization_metrics/metrics/__init__.py
sm_diarization_metrics/metrics/_version.py
sm_diarization_metrics/metrics/base.py
sm_diarization_metrics/metrics/binary_classification.py
sm_diarization_metrics/metrics/detection.py
sm_diarization_metrics/metrics/diarization.py
sm_diarization_metrics/metrics/identification.py
sm_diarization_metrics/metrics/matcher.py
sm_diarization_metrics/metrics/segmentation.py
sm_diarization_metrics/metrics/spotting.py
sm_diarization_metrics/metrics/utils.py
sm_diarization_metrics/metrics/words.py
sm_diarization_metrics/metrics/errors/__init__.py
sm_diarization_metrics/metrics/errors/identification.py
sm_diarization_metrics/metrics/errors/segmentation.py
sm_diarization_metrics/metrics/plot/__init__.py
sm_diarization_metrics/metrics/plot/binary_classification.py
speechmatics_diarization_metrics-0.0.2.dist-info/METADATA
speechmatics_diarization_metrics-0.0.2.dist-info/WHEEL
speechmatics_diarization_metrics-0.0.2.dist-info/top_level.txt
speechmatics_diarization_metrics-0.0.2.dist-info/RECORD
