Metadata-Version: 2.1
Name: speechmatics-diarization-metrics
Version: 0.0.2
Summary: Python module for evaluating speaker diarization.
Home-page: UNKNOWN
Author: Speechmatics
Author-email: support@speechmatics.com
License: Speechmatics Proprietary License
Platform: linux
Requires-Python: >=3.5
Requires-Dist: pyannote.core
Requires-Dist: pyannote.database
Requires-Dist: docopt
Requires-Dist: tabulate
